LICENSE.txt
MANIFEST.in
README.rst
setup.py
fnalmilc/__init__.py
fnalmilc/app.py
fnalmilc/formfactors-bs2k.py
fnalmilc/formfactors.py
fnalmilc/pheno.py
fnalmilc.egg-info/PKG-INFO
fnalmilc.egg-info/SOURCES.txt
fnalmilc.egg-info/dependency_links.txt
fnalmilc.egg-info/entry_points.txt
fnalmilc.egg-info/not-zip-safe
fnalmilc.egg-info/requires.txt
fnalmilc.egg-info/top_level.txt
fnalmilc/constants/__init__.py
fnalmilc/constants/constants_b2d_2012.py
fnalmilc/constants/constants_bs2ds_2012.py
fnalmilc/constants/constants_bs2k_2018.py
fnalmilc/tests/__init__.py
fnalmilc/tests/test_formfactors.py