Metadata-Version: 1.0
Name: fnalmilc
Version: 0.1
Summary: fnalmilc is an application written in Python thatconstructs physical quantities using results obtained by theFermilab Lattice and MILC Collaborations.
Home-page: https://github.com/sdliuyuzhi/fnalmilc
Author: Yuzhi Liu
Author-email: liuyuzhi83@gmail.com
License: BSD 2-Clause License
Keywords: form factor,semileptonic,Bs2K,FNAL,MILC,Fermilab,Lattice,QCD,phenomenology,decay rate
Platform: UNKNOWN
